{
  "neoforge-21.1.146 (modloader)": {
    "modId": "neoforge",
    "version": "neoforge-21.1.146"
  },
  "[NeoForge] mythsandlegends-0.0.5.1.jar": {
    "modId": "mythsandlegends",
    "version": "0.0.5.1"
  },
  "accelerated-decay-neoforge-21.0.0.jar": {
    "modId": "accelerateddecay",
    "version": "21.0.0"
  },
  "additional_lights-neoforge-1.21-2.1.9.jar": {
    "modId": "additional_lights",
    "version": "2.1.9"
  },
  "AdvancementPlaques-1.21.1-neoforge-1.6.8.jar": {
    "modId": "advancementplaques",
    "version": "1.6.8"
  },
  "aether-1.21.1-1.5.8-neoforge.jar": {
    "modId": "aether",
    "version": "1.5.8"
  },
  "AI-Improvements-1.21-0.5.3.jar": {
    "modId": "aiimprovements",
    "version": "0.5.3"
  },
  "almanac-1.21.x-neoforge-1.0.2.jar": {
    "modId": "almanac",
    "version": "1.0.2"
  },
  "alternate_current-mc1.21-1.9.0.jar": {
    "modId": "alternate_current",
    "version": "1.9.0"
  },
  "amber-neoforge-1.21.1-3.0.0+1.21.1.jar": {
    "modId": "amber",
    "version": "3.0.0+1.21.1"
  },
  "AmbientSounds_NEOFORGE_v6.1.8_mc1.21.1.jar": {
    "modId": "ambientsounds",
    "version": "6.1.8"
  },
  "amendments-1.21-1.2.24-neoforge.jar": {
    "modId": "amendments",
    "version": "1.21-1.2.24"
  },
  "Apotheosis-1.21.1-8.3.1.jar": {
    "modId": "apotheosis",
    "version": "8.3.1"
  },
  "ApothicAttributes-1.21.1-2.8.0.jar": {
    "modId": "apothic_attributes",
    "version": "2.8.0"
  },
  "ApothicEnchanting-1.21.1-1.4.0.jar": {
    "modId": "apothic_enchanting",
    "version": "1.4.0"
  },
  "ApothicSpawners-1.21.1-1.3.0.jar": {
    "modId": "apothic_spawners",
    "version": "1.3.0"
  },
  "appleskin-neoforge-mc1.21-3.0.5.jar": {
    "modId": "appleskin",
    "version": "3.0.5+mc1.21"
  },
  "architectury-13.0.8-neoforge.jar": {
    "modId": "architectury",
    "version": "13.0.8"
  },
  "arkane domains neoforge-1.21.1.jar": {
    "modId": "arkane_domains",
    "version": "1.0.0"
  },
  "armoroftheages-neoforge-1.21.1-1.5.3.jar": {
    "modId": "armoroftheages",
    "version": "1.5.3"
  },
  "ArmorStatues-v21.1.0-1.21.1-NeoForge.jar": {
    "modId": "armorstatues",
    "version": "21.1.0"
  },
  "artifacts-neoforge-12.1.5.jar": {
    "modId": "artifacts",
    "version": "12.1.5"
  },
  "arts_and_crafts-neoforge-1.21.1-1.4.3.jar": {
    "modId": "arts_and_crafts",
    "version": "1.4.3"
  },
  "astages-1.2.1-1.21.1.jar": {
    "modId": "astages",
    "version": "1.2.1-1.21.1"
  },
  "atlas_api-1.21-1.0.2.jar": {
    "modId": "atlas_api",
    "version": "1.21-1.0.2"
  },
  "attributefix-neoforge-1.21.1-21.1.2.jar": {
    "modId": "attributefix",
    "version": "21.1.2"
  },
  "azurelib-neo-1.21.1-3.0.11.jar": {
    "modId": "azurelib",
    "version": "3.0.11"
  },
  "BadOptimizations-2.2.1-1.21.1.jar": {
    "modId": "badoptimizations",
    "version": "2.2.1"
  },
  "balm-neoforge-1.21.1-21.0.39.jar": {
    "modId": "balm",
    "version": "21.0.39"
  },
  "bcc-21.1.3+mc1.21.1.jar": {
    "modId": "bcc",
    "version": "21.1.3"
  },
  "BetterAdvancements-NeoForge-1.21.1-0.4.3.21.jar": {
    "modId": "betteradvancements",
    "version": "0.4.3.21"
  },
  "betterchunkloading-1.21-5.4.jar": {
    "modId": "betterchunkloading",
    "version": "5.4"
  },
  "bettercombat-neoforge-2.1.3+1.21.1.jar": {
    "modId": "bettercombat",
    "version": "2.1.3+1.21.1"
  },
  "BetterThirdPerson-neoforge-1.9.0.jar": {
    "modId": "betterthirdperson",
    "version": "1.9.0"
  },
  "bloxysstructures-1.17.1-neoforge-1.21.1.jar": {
    "modId": "bloxysstructures",
    "version": "1.17.1"
  },
  "BOMD-NeoForge-1.21-1.3.2.jar": {
    "modId": "bosses_of_mass_destruction",
    "version": "1.3.2"
  },
  "bonded-neoforge-1.21.1-1.2.2+1.21.1.jar": {
    "modId": "bonded",
    "version": "1.2.2+1.21.1"
  },
  "bookshelf-neoforge-1.21.1-21.1.58.jar": {
    "modId": "bookshelf",
    "version": "21.1.58"
  },
  "CerbonsAPI-NeoForge-1.21-1.2.0.jar": {
    "modId": "cerbons_api",
    "version": "1.2.0"
  },
  "chalk-1.6.9.jar": {
    "modId": "chalk",
    "version": "1.6.9"
  },
  "chat_heads-0.13.17-neoforge-1.21.jar": {
    "modId": "chat_heads",
    "version": "0.13.17"
  },
  "cherishedworlds-neoforge-10.1.1+1.21.1.jar": {
    "modId": "cherishedworlds",
    "version": "10.1.1+1.21.1"
  },
  "chunkactivitytracker-neoforge-1.0.1-1.21.1.jar": {
    "modId": "chunkactivitytracker",
    "version": "1.0.1"
  },
  "chunksending-1.21-2.8.jar": {
    "modId": "chunksending",
    "version": "2.8"
  },
  "clickadv-1.21-3.8.jar": {
    "modId": "clickadv",
    "version": "3.8"
  },
  "clientcrafting-1.21-1.8.jar": {
    "modId": "clientcrafting",
    "version": "1.8"
  },
  "cloth-config-15.0.140-neoforge.jar": {
    "modId": "cloth_config",
    "version": "15.0.140"
  },
  "Clumps-neoforge-1.21.1-19.0.0.1.jar": {
    "modId": "clumps",
    "version": "19.0.0.1"
  },
  "cobblegengalore-1.21.1-0.2.0.jar": {
    "modId": "cobblegengalore",
    "version": "1.21.1-0.2.0"
  },
  "codex_of_champions-1.1.0.jar": {
    "modId": "codex_of_champions",
    "version": "1.1.0"
  },
  "collective-1.21.1-8.3.jar": {
    "modId": "collective",
    "version": "8.3"
  },
  "collectorsalbum-neoforge-1.21.1-2.2.0.jar": {
    "modId": "collectorsalbum",
    "version": "2.2.0"
  },
  "combat_roll-neoforge-2.0.2+1.21.1.jar": {
    "modId": "combat_roll",
    "version": "2.0.2+1.21.1"
  },
  "comforts-neoforge-9.0.3+1.21.1.jar": {
    "modId": "comforts",
    "version": "9.0.3+1.21.1"
  },
  "configuration-neoforge-1.21.1-3.1.0.jar": {
    "modId": "configuration",
    "version": "3.1.0"
  },
  "connectivity-1.21.1-7.1.jar": {
    "modId": "connectivity",
    "version": "7.1"
  },
  "Controlling-neoforge-1.21.1-19.0.5.jar": {
    "modId": "controlling",
    "version": "19.0.5"
  },
  "Corgilib-NeoForge-1.21.1-5.0.0.3.jar": {
    "modId": "corgilib",
    "version": "5.0.0.3"
  },
  "coroutil-neoforge-1.21.0-1.3.8.jar": {
    "modId": "coroutil",
    "version": "1.21.0-1.3.8"
  },
  "cosmeticarmorreworked-1.21.1-v1-neoforge.jar": {
    "modId": "cosmeticarmorreworked",
    "version": "1.21.1-v1-neoforge"
  },
  "CosmeticArmours - 1.5.2.1 - 1.21.1 - NeoForge.jar": {
    "modId": "cosmeticarmoursmod",
    "version": "1.5.2.1"
  },
  "craftingtweaks-neoforge-1.21.1-21.1.5.jar": {
    "modId": "craftingtweaks",
    "version": "21.1.5"
  },
  "crash_assistant-neoforge-1.21.1-1.7.6.jar": {
    "modId": "crash_assistant",
    "version": "1.7.6"
  },
  "create-1.21.1-6.0.4.jar": {
    "modId": "create",
    "version": "6.0.4"
  },
  "create-dragons-plus-1.3.4.jar": {
    "modId": "create_dragons_plus",
    "version": "1.3.4"
  },
  "create-enchantment-industry-2.0.8.jar": {
    "modId": "create_enchantment_industry",
    "version": "2.0.8"
  },
  "create-stuff-additions1.21.1_v2.1.0d.jar": {
    "modId": "create_sa",
    "version": "2.1.0."
  },
  "create_cardboarded_conveynience-0.0.3b.jar": {
    "modId": "create_cardboarded_conveynience",
    "version": "0.0.3b"
  },
  "Create_Desires-2-Dreams-1.21.1-2.0.0.jar": {
    "modId": "create_d2d",
    "version": "2.0.0"
  },
  "create_generators-1.0.5-neoforge-1.21.1.jar": {
    "modId": "create_generators",
    "version": "1.0.5"
  },
  "create_mechanical_extruder-1.21.1-2.0.5-6.0.4.jar": {
    "modId": "create_mechanical_extruder",
    "version": "1.21.1-2.0.5-6.0.4"
  },
  "create_pattern_schematics-2.0.6.jar": {
    "modId": "create_pattern_schematics",
    "version": "2.0.6"
  },
  "create_things_and_misc-4.0-neoforge-1.21.1.jar": {
    "modId": "create_things_and_misc",
    "version": "1.0.0"
  },
  "createaddition-1.4.0.jar": {
    "modId": "createaddition"
  },
  "createchromaticreturn-1.0.1-neoforge-1.21.1.jar": {
    "modId": "createchromaticreturn",
    "version": "1.0.0"
  },
  "createcompounds-1.21.1-NeoForge-1.0.0.jar": {
    "modId": "createcompounds",
    "version": "1.0.0"
  },
  "createteleporters2.4-1.21.1.jar": {
    "modId": "createteleporters",
    "version": "2.4"
  },
  "CreativeCore_NEOFORGE_v2.13.2_mc1.21.1.jar": {
    "modId": "creativecore",
    "version": "2.13.2"
  },
  "cristellib-neoforge-1.2.8.jar": {
    "modId": "cristellib",
    "version": "1.2.8"
  },
  "cupboard-1.21-2.9.jar": {
    "modId": "cupboard",
    "version": "2.9"
  },
  "curios-neoforge-9.4.2+1.21.1.jar": {
    "modId": "curios",
    "version": "9.4.2+1.21.1"
  },
  "deeperdarker-neoforge-1.21-1.3.4.jar": {
    "modId": "deeperdarker",
    "version": "1.3.4"
  },
  "Ding-1.21-NeoForge-1.5.0.jar": {
    "modId": "ding",
    "version": "1.5.0"
  },
  "does_it_tick-neoforge-1.1.4-1.21.1.jar": {
    "modId": "does_it_tick",
    "version": "1.1.4"
  },
  "doubledoors-1.21.1-7.0.jar": {
    "modId": "doubledoors",
    "version": "7.0"
  },
  "drippyloadingscreen_neoforge_3.0.12_MC_1.21.1.jar": {
    "modId": "drippyloadingscreen",
    "version": "3.0.12"
  },
  "dummmmmmy-1.21-2.0.7-neoforge.jar": {
    "modId": "dummmmmmy",
    "version": "1.21-2.0.7"
  },
  "EnchantingInfuser-v21.1.0-1.21.1-NeoForge.jar": {
    "modId": "enchantinginfuser",
    "version": "21.1.0"
  },
  "enchantmentmachine-1.21.1-1.1.5-beta.1.jar": {
    "modId": "enchantmentmachine",
    "version": "1.1.5-beta.1"
  },
  "enchdesc-neoforge-1.21.1-21.1.7.jar": {
    "modId": "enchdesc",
    "version": "21.1.7"
  },
  "endrem-neoforge-1.21.X-6.0.2.jar": {
    "modId": "endrem",
    "version": "6.0.2"
  },
  "entityculling-neoforge-1.7.4-mc1.21.jar": {
    "modId": "entityculling",
    "version": "1.7.4"
  },
  "EquipmentCompare-1.21.1-neoforge-1.3.13.jar": {
    "modId": "equipmentcompare",
    "version": "1.3.13"
  },
  "fancymenu_neoforge_3.5.0_MC_1.21.1.jar": {
    "modId": "fancymenu",
    "version": "3.5.0"
  },
  "FarmersDelight-1.21.1-1.2.7.jar": {
    "modId": "farmersdelight",
    "version": "1.2.7"
  },
  "FarmersStructures-1.0.1-1.21.1_neoforge.jar": {
    "modId": "farmers_structures",
    "version": "1.0.0"
  },
  "farmingforblockheads-neoforge-1.21.1-21.1.8.jar": {
    "modId": "farmingforblockheads",
    "version": "21.1.8"
  },
  "farsight-1.21-3.8.jar": {
    "modId": "farsight_view",
    "version": "3.8"
  },
  "fastasyncworldsave-1.21-2.4.jar": {
    "modId": "fastasyncworldsave",
    "version": "2.4"
  },
  "FastFurnace-1.21.1-9.0.0.jar": {
    "modId": "fastfurnace",
    "version": "9.0.0"
  },
  "FastWorkbench-1.21-9.1.2.jar": {
    "modId": "fastbench",
    "version": "9.1.2"
  },
  "ferritecore-7.0.2-neoforge.jar": {
    "modId": "ferritecore",
    "version": "7.0.2"
  },
  "foodeffecttooltips+neoforge-1.21.1-1.4.0.jar": {
    "modId": "foodeffecttooltips",
    "version": "1.4.0"
  },
  "ForgeConfigAPIPort-v21.1.3-1.21.1-NeoForge.jar": {
    "modId": "forgeconfigapiport",
    "version": "21.1.3"
  },
  "framework-neoforge-1.21.1-0.9.4.jar": {
    "modId": "framework",
    "version": "0.9.4"
  },
  "ftb-chunks-neoforge-2101.1.8.jar": {
    "modId": "ftbchunks",
    "version": "2101.1.8"
  },
  "ftb-library-neoforge-2101.1.12.jar": {
    "modId": "ftblibrary",
    "version": "2101.1.12"
  },
  "ftb-quests-neoforge-2101.1.9.jar": {
    "modId": "ftbquests",
    "version": "2101.1.9"
  },
  "ftb-teams-neoforge-2101.1.2.jar": {
    "modId": "ftbteams",
    "version": "2101.1.2"
  },
  "fusion-1.2.7-neoforge-mc1.21.jar": {
    "modId": "fusion",
    "version": "1.2.7"
  },
  "fzzy_config-0.6.9+1.21+neoforge.jar": {
    "modId": "fzzy_config",
    "version": "0.6.9+1.21+neoforge"
  },
  "garnished-2.1.2+1.21.1-neoforged.jar": {
    "modId": "garnished",
    "version": "2.1.2"
  },
  "geckolib-neoforge-1.21.1-4.7.5.1.jar": {
    "modId": "geckolib",
    "version": "4.7.5.1"
  },
  "Geophilic v3.4 f15-71.mod.jar": {
    "modId": "geophilic",
    "version": "3.4"
  },
  "gpumemleakfix-1.21-1.8.jar": {
    "modId": "gpumemleakfix",
    "version": "1.8"
  },
  "hearts_bottle-1.0.2-neoforge-1.21.1.jar": {
    "modId": "hearts_bottle",
    "version": "1.0.0"
  },
  "Highlighter-1.21-neoforge-1.1.11.jar": {
    "modId": "highlighter",
    "version": "1.1.11"
  },
  "HostileNeuralNetworks-1.21.1-6.2.0.jar": {
    "modId": "hostilenetworks",
    "version": "6.2.0"
  },
  "IceAndFireCE-1.0-beta.8-1.21.1-neoforge.jar": {
    "modId": "iceandfire",
    "version": "1.0-beta.8"
  },
  "Iceberg-1.21.1-neoforge-1.3.2.jar": {
    "modId": "iceberg",
    "version": "1.3.2"
  },
  "iChunUtil-1.21-NeoForge-1.0.3.jar": {
    "modId": "ichunutil",
    "version": "1.0.3"
  },
  "ImmediatelyFast-NeoForge-1.6.5+1.21.1.jar": {
    "modId": "immediatelyfast",
    "version": "1.6.5+1.21.1"
  },
  "immersive_aircraft-1.2.2+1.21.1-neoforge.jar": {
    "modId": "immersive_aircraft",
    "version": "1.2.2+1.21.1"
  },
  "ImmersiveUI-NEOFORGE-0.3.0.jar": {
    "modId": "immersiveui",
    "version": "0.3.0"
  },
  "inventorysorter-1.21-24.0.20.jar": {
    "modId": "inventorysorter",
    "version": "24.0.20"
  },
  "iris-neoforge-1.8.8+mc1.21.1.jar": {
    "modId": "iris",
    "version": "1.8.8+mc1.21.1"
  },
  "irons_jewelry-1.21.1-1.1.0.jar": {
    "modId": "irons_jewelry",
    "version": "1.21.1-1.1.0"
  },
  "irons_spellbooks-1.21.1-3.11.0.jar": {
    "modId": "irons_spellbooks",
    "version": "1.21.1-3.11.0"
  },
  "Jade-1.21.1-NeoForge-15.10.0.jar": {
    "modId": "jade",
    "version": "15.10.0+neoforge"
  },
  "jei-1.21.1-neoforge-19.21.0.247.jar": {
    "modId": "jei",
    "version": "19.21.0.247"
  },
  "jinxedlib-neoforge-1.21.1-1.0.3.jar": {
    "modId": "jinxedlib",
    "version": "1.0.3"
  },
  "Jupiter-2.1-neoforge.jar": {
    "modId": "jupiter",
    "version": "2.1"
  },
  "JustEnoughProfessions-neoforge-1.21.1-4.0.4.jar": {
    "modId": "justenoughprofessions",
    "version": "4.0.4"
  },
  "JustEnoughResources-NeoForge-1.21.1-1.6.0.13.jar": {
    "modId": "jeresources",
    "version": "1.6.0.13"
  },
  "konkrete_neoforge_1.9.9_MC_1.21.jar": {
    "modId": "konkrete",
    "version": "1.9.9"
  },
  "kotlinforforge-5.7.0-all.jar": {},
  "kubejs-neoforge-2101.7.1-build.181.jar": {
    "modId": "kubejs",
    "version": "2101.7.1-build.181"
  },
  "L_Ender\u0027s Cataclysm-2.65-1.21.1.jar": {
    "modId": "cataclysm",
    "version": "2.65-1.21.1"
  },
  "LegendaryTooltips-1.21.1-neoforge-1.5.5.jar": {
    "modId": "legendarytooltips",
    "version": "1.5.5"
  },
  "letmedespawn-1.21.x-neoforge-1.5.0.jar": {
    "modId": "letmedespawn",
    "version": "1.5.0"
  },
  "lionfishapi-2.6.jar": {
    "modId": "lionfishapi",
    "version": "2.6"
  },
  "lootjs-neoforge-1.21.1-3.4.0.jar": {
    "modId": "lootjs",
    "version": "1.21.1-3.4.0"
  },
  "lootr-neoforge-1.21-1.10.35.91.jar": {
    "modId": "lootr",
    "version": "1.21-1.10.35.91"
  },
  "lukis-grand-capitals-1.1.1.jar": {
    "modId": "mr_lukis_grandcapitals",
    "version": "1.1.1"
  },
  "man_of_many_planes-0.2.1+1.21.1-neoforge.jar": {
    "modId": "man_of_many_planes",
    "version": "0.2.1+1.21.1"
  },
  "melody_neoforge_1.0.10_MC_1.21.jar": {
    "modId": "melody",
    "version": "1.0.10"
  },
  "memorysettings-1.21-5.9.jar": {
    "modId": "memorysettings",
    "version": "5.9"
  },
  "mobs_of_mythology-neoforge-1.21.1-2.2.2.jar": {
    "modId": "mobs_of_mythology",
    "version": "2.2.2"
  },
  "modernfix-neoforge-5.21.0+mc1.21.1.jar": {
    "modId": "modernfix",
    "version": "5.21.0+mc1.21.1"
  },
  "modernworldcreation_neoforge_2.0.1_MC_1.21.1.jar": {
    "modId": "modernworldcreation",
    "version": "2.0.1"
  },
  "molten_vents-1.21.1-2.0.9.jar": {
    "modId": "molten_vents",
    "version": "2.0.9"
  },
  "moonlight-1.21-2.18.8-neoforge.jar": {
    "modId": "moonlight",
    "version": "1.21-2.18.8"
  },
  "moreoverlays-1.23.2-mc1.21-neoforge.jar": {
    "modId": "moreoverlays",
    "version": "1.23.2-neoforge"
  },
  "MouseTweaks-neoforge-mc1.21-2.26.1.jar": {
    "modId": "mousetweaks",
    "version": "2.26.1"
  },
  "Neruina-2.2.11-neoforge+1.21.jar": {
    "modId": "neruina",
    "version": "2.2.11"
  },
  "netherportalfix-neoforge-1.21.1-21.1.1.jar": {
    "modId": "netherportalfix",
    "version": "21.1.1"
  },
  "noisium-neoforge-2.3.0+mc1.21-1.21.1.jar": {
    "modId": "noisium",
    "version": "2.3.0+mc1.21-1.21.1"
  },
  "notenoughanimations-neoforge-1.9.3-mc1.21.jar": {
    "modId": "notenoughanimations",
    "version": "1.9.3"
  },
  "OctoLib-NEOFORGE-0.5.0.1.jar": {
    "modId": "octolib",
    "version": "0.5.0.1"
  },
  "Oh-The-Biomes-Weve-Gone-NeoForge-2.3.13.jar": {
    "modId": "biomeswevegone",
    "version": "2.3.13"
  },
  "Oh-The-Trees-Youll-Grow-neoforge-1.21.1-5.0.10.jar": {
    "modId": "ohthetreesyoullgrow",
    "version": "5.0.10"
  },
  "omni_util-1.0.2.jar": {
    "modId": "omni_util",
    "version": "1.0.2"
  },
  "OpenBlocksTrophies-1.21-5.1.6.jar": {
    "modId": "obtrophies",
    "version": "1.21-5.1.6"
  },
  "oracle_index-neoforge-0.2.0.jar": {
    "modId": "oracle_index",
    "version": "0.2.0"
  },
  "OverflowingBars-v21.1.1-1.21.1-NeoForge.jar": {
    "modId": "overflowingbars",
    "version": "21.1.1"
  },
  "owo-lib-neoforge-0.12.15.1-beta.3+1.21.jar": {
    "modId": "owo",
    "version": "0.12.15.1-beta.3+1.21"
  },
  "packetfixer-neoforge-2.1.0-1.21-to-1.21.3.jar": {
    "modId": "packetfixer",
    "version": "2.1.0"
  },
  "Patchouli-1.21-88-NEOFORGE.jar": {
    "modId": "patchouli",
    "version": "1.21-88-NEOFORGE"
  },
  "Paxi-1.21.1-NeoForge-5.1.2.jar": {
    "modId": "paxi",
    "version": "1.21.1-NeoForge-5.1.2"
  },
  "PickUpNotifier-v21.1.1-1.21.1-NeoForge.jar": {
    "modId": "pickupnotifier",
    "version": "21.1.1"
  },
  "Placebo-1.21.1-9.8.0.jar": {
    "modId": "placebo",
    "version": "9.8.0"
  },
  "player-animation-lib-forge-2.0.1+1.21.1.jar": {
    "modId": "playeranimator",
    "version": "2.0.1+1.21.1"
  },
  "polymorph-neoforge-1.0.9+1.21.1.jar": {
    "modId": "polymorph",
    "version": "1.0.9+1.21.1"
  },
  "prickle-neoforge-1.21.1-21.1.6.jar": {
    "modId": "prickle",
    "version": "21.1.6"
  },
  "Prism-1.21.1-neoforge-1.0.11.jar": {
    "modId": "prism",
    "version": "1.0.11"
  },
  "PuzzlesLib-v21.1.33-1.21.1-NeoForge.jar": {
    "modId": "puzzleslib",
    "version": "21.1.33"
  },
  "redirected-neoforge-1.0.0-1.21.1.jar": {
    "modId": "redirected",
    "version": "1.0.0"
  },
  "reeses-sodium-options-neoforge-1.8.3+mc1.21.4.jar": {
    "modId": "reeses_sodium_options",
    "version": "1.8.3+mc1.21.4"
  },
  "resourcefulconfig-neoforge-1.21-3.0.9.jar": {
    "modId": "resourcefulconfig",
    "version": "3.0.9"
  },
  "resourcefullib-neoforge-1.21-3.0.12.jar": {
    "modId": "resourcefullib",
    "version": "3.0.12"
  },
  "rhino-2101.2.7-build.74.jar": {
    "modId": "rhino",
    "version": "2101.2.7-build.74"
  },
  "rpg_health_overhaul-1.3-neoforge-1.21.1.jar": {
    "modId": "rpg_health_overhaul",
    "version": "1.3"
  },
  "scholar-neoforge-1.21.1-1.1.6.jar": {
    "modId": "scholar",
    "version": "1.1.6"
  },
  "Searchables-neoforge-1.21.1-1.0.2.jar": {
    "modId": "searchables",
    "version": "1.0.2"
  },
  "showcaseitem-1.21.1-1.1.0.jar": {
    "modId": "showcaseitem",
    "version": "1.21.1-1.1.0"
  },
  "simplelootviewer-neoforge-1.21.1-21.1.2.jar": {
    "modId": "simplelootviewer",
    "version": "21.1.2"
  },
  "simplyswords-neoforge-1.60.11-1.21.1.jar": {
    "modId": "simplyswords",
    "version": "1.60.11-1.21.1"
  },
  "skinlayers3d-neoforge-1.7.5-mc1.21.jar": {
    "modId": "skinlayers3d",
    "version": "1.7.5"
  },
  "SmartBrainLib-neoforge-1.21.1-1.16.7.jar": {
    "modId": "smartbrainlib",
    "version": "1.16.7"
  },
  "smoothchunk-1.21-4.1.jar": {
    "modId": "smoothchunk",
    "version": "4.1"
  },
  "sodium-neoforge-0.6.13+mc1.21.1.jar": {
    "modId": "sodium",
    "version": "0.6.13+mc1.21.1"
  },
  "sodiumdynamiclights-neoforge-1.0.10-1.21.1.jar": {
    "modId": "sodiumdynamiclights",
    "version": "1.0.9"
  },
  "sodiumextras-neoforge-1.0.8-1.21.1.jar": {
    "modId": "sodiumextras",
    "version": "1.0.7"
  },
  "sodiumoptionsapi-neoforge-1.0.10-1.21.1.jar": {
    "modId": "sodiumoptionsapi",
    "version": "1.0.10"
  },
  "solcarrot-1.21.1-1.16.5.jar": {
    "modId": "solcarrot",
    "version": "1.16.5"
  },
  "sophisticatedbackpacks-1.21.1-3.24.9.1228.jar": {
    "modId": "sophisticatedbackpacks",
    "version": "3.24.9"
  },
  "sophisticatedbackpackscreateintegration-1.21.1-0.1.1.5.jar": {
    "modId": "sophisticatedbackpackscreateintegration",
    "version": "0.1.1"
  },
  "sophisticatedcore-1.21.1-1.3.27.951.jar": {
    "modId": "sophisticatedcore",
    "version": "1.3.27"
  },
  "sophisticatedstorage-1.21.1-1.4.21.1123.jar": {
    "modId": "sophisticatedstorage",
    "version": "1.4.21"
  },
  "sophisticatedstoragecreateintegration-1.21.1-0.1.8.27.jar": {
    "modId": "sophisticatedstoragecreateintegration",
    "version": "0.1.8"
  },
  "sound-physics-remastered-neoforge-1.21.1-1.4.10.jar": {
    "modId": "sound_physics_remastered",
    "version": "1.21.1-1.4.10"
  },
  "spark-1.10.124-neoforge.jar": {
    "modId": "spark",
    "version": "1.10.124"
  },
  "supplementaries-1.21-3.1.7-neoforge.jar": {
    "modId": "supplementaries",
    "version": "1.21-3.1.7"
  },
  "TerraBlender-neoforge-1.21.1-4.1.0.8.jar": {
    "modId": "terrablender",
    "version": "4.1.0.8"
  },
  "toofast-1.21.0-0.4.3.5.jar": {
    "modId": "toofast",
    "version": "0.4.3.5"
  },
  "torchmaster-neoforge-1.21.1-21.1.5-beta.jar": {
    "modId": "torchmaster",
    "version": "21.1.5-beta"
  },
  "towers_of_chaos-1.0.1-neoforge-1.21.1.jar": {
    "modId": "towers_of_chaos",
    "version": "1.0.0"
  },
  "TravelersTitles-1.21.1-NeoForge-5.1.3.jar": {
    "modId": "travelerstitles",
    "version": "1.21.1-NeoForge-5.1.3"
  },
  "treasuredistance-1.0.jar": {
    "modId": "treasuredistance",
    "version": "1.0"
  },
  "trophymanager-1.21.1-2.2.4.jar": {
    "modId": "trophymanager",
    "version": "1.21.1-2.2.4"
  },
  "txnilib-neoforge-1.0.23-1.21.1.jar": {
    "modId": "txnilib",
    "version": "1.0.23"
  },
  "uranus-2.3-1.21.1-neoforge.jar": {
    "modId": "uranus",
    "version": "2.3"
  },
  "variantsandventures-neoforge-mc1.21.1-1.0.12.jar": {
    "modId": "variantsandventures",
    "version": "1.0.12"
  },
  "VisualWorkbench-v21.1.0-1.21.1-NeoForge.jar": {
    "modId": "visualworkbench",
    "version": "21.1.0"
  },
  "watut-neoforge-1.21.0-1.2.7.jar": {
    "modId": "watut",
    "version": "1.21.0-1.2.7"
  },
  "waystones-neoforge-1.21.1-21.1.15.jar": {
    "modId": "waystones",
    "version": "21.1.15"
  },
  "wits-1.3.0+1.21-neoforge.jar": {
    "modId": "wits",
    "version": "1.3.0+1.21-neoforge"
  },
  "Xaeros_Minimap_25.2.0_NeoForge_1.21.jar": {
    "modId": "xaerominimap",
    "version": "25.2.0"
  },
  "yet_another_config_lib_v3-3.6.6+1.21.1-neoforge.jar": {
    "modId": "yet_another_config_lib_v3",
    "version": "3.6.6+1.21.1-neoforge"
  },
  "youre-in-grave-danger-neoforge-2.0.11.jar": {
    "modId": "yigd",
    "version": "2.0.11"
  },
  "YungsApi-1.21.1-NeoForge-5.1.4.jar": {
    "modId": "yungsapi",
    "version": "1.21.1-NeoForge-5.1.4"
  }
}